trains/__init__.py
trains/errors.py
trains/logger.py
trains/model.py
trains/task.py
trains/task_parameters.py
trains/version.py
trains/automation/__init__.py
trains/automation/auto_scaler.py
trains/automation/aws_auto_scaler.py
trains/automation/controller.py
trains/automation/job.py
trains/automation/monitor.py
trains/automation/optimization.py
trains/automation/parameters.py
trains/automation/hpbandster/__init__.py
trains/automation/hpbandster/bandster.py
trains/automation/optuna/__init__.py
trains/automation/optuna/optuna.py
trains/backend_api/__init__.py
trains/backend_api/api_proxy.py
trains/backend_api/utils.py
trains/backend_api/config/__init__.py
trains/backend_api/config/default/api.conf
trains/backend_api/config/default/logging.conf
trains/backend_api/schema/__init__.py
trains/backend_api/schema/action.py
trains/backend_api/schema/service.py
trains/backend_api/services/__init__.py
trains/backend_api/services/v2_1/__init__.py
trains/backend_api/services/v2_1/auth.py
trains/backend_api/services/v2_1/events.py
trains/backend_api/services/v2_1/models.py
trains/backend_api/services/v2_1/projects.py
trains/backend_api/services/v2_1/tasks.py
trains/backend_api/services/v2_2/__init__.py
trains/backend_api/services/v2_2/auth.py
trains/backend_api/services/v2_2/events.py
trains/backend_api/services/v2_2/models.py
trains/backend_api/services/v2_2/projects.py
trains/backend_api/services/v2_2/tasks.py
trains/backend_api/services/v2_3/__init__.py
trains/backend_api/services/v2_3/auth.py
trains/backend_api/services/v2_3/events.py
trains/backend_api/services/v2_3/models.py
trains/backend_api/services/v2_3/projects.py
trains/backend_api/services/v2_3/tasks.py
trains/backend_api/services/v2_4/__init__.py
trains/backend_api/services/v2_4/auth.py
trains/backend_api/services/v2_4/events.py
trains/backend_api/services/v2_4/models.py
trains/backend_api/services/v2_4/projects.py
trains/backend_api/services/v2_4/queues.py
trains/backend_api/services/v2_4/tasks.py
trains-0.16.3.dist-info/LICENSE
trains-0.16.3.dist-info/METADATA
trains-0.16.3.dist-info/WHEEL
trains-0.16.3.dist-info/entry_points.txt
trains-0.16.3.dist-info/top_level.txt
trains-0.16.3.dist-info/RECORD
