Metadata-Version: 2.1
Name: trains
Version: 0.16.3
Summary: TRAINS - Auto-Magical Experiment Manager & Version Control for AI
Home-page: https://github.com/allegroai/trains
Author: Allegroai
Author-email: trains@allegro.ai
License: Apache License 2.0
Keywords: trains development machine deep learning version control machine-learning machinelearning deeplearning deep-learning experiment-manager experimentmanager
Platform: UNKNOWN
Classifier: Development Status :: 4 - Beta
Classifier: Intended Audience :: Developers
Classifier: Intended Audience :: Science/Research
Classifier: Operating System :: POSIX :: Linux
Classifier: Operating System :: MacOS :: MacOS X
Classifier: Operating System :: Microsoft
Classifier: Topic :: Scientific/Engineering :: Artificial Intelligence
Classifier: Topic :: Software Development
Classifier: Topic :: Software Development :: Version Control
Classifier: Topic :: System :: Logging
Classifier: Topic :: System :: Monitoring
Classifier: Programming Language :: Python :: 2.7
Classifier: Programming Language :: Python :: 3.5
Classifier: Programming Language :: Python :: 3.6
Classifier: Programming Language :: Python :: 3.7
Classifier: Programming Language :: Python :: 3.8
Classifier: License :: OSI Approved :: Apache Software License
Requires-Dist: attrs (>=18.0)
Requires-Dist: funcsigs (>=1.0)
Requires-Dist: furl (>=2.0.0)
Requires-Dist: future (>=0.16.0)
Requires-Dist: humanfriendly (>=2.1)
Requires-Dist: jsonschema (>=2.6.0)
Requires-Dist: numpy (>=1.10)
Requires-Dist: pathlib2 (>=2.3.0)
Requires-Dist: Pillow (>=4.1.1)
Requires-Dist: plotly (>=3.9.0)
Requires-Dist: psutil (>=3.4.2)
Requires-Dist: pyparsing (>=2.0.3)
Requires-Dist: python-dateutil (>=2.6.1)
Requires-Dist: pyjwt (>=1.6.4)
Requires-Dist: PyYAML (>=3.12)
Requires-Dist: requests-file (>=1.4.2)
Requires-Dist: requests (>=2.20.0)
Requires-Dist: six (>=1.11.0)
Requires-Dist: tqdm (>=4.19.5)
Requires-Dist: urllib3 (>=1.21.1)
Requires-Dist: backports.functools-lru-cache (>=1.0.2) ; python_version < "3"
Requires-Dist: futures (>=3.0.5) ; python_version < "3"
Requires-Dist: typing (>=3.6.4) ; python_version < "3.5"
Requires-Dist: enum34 (>=0.9) ; python_version < "3.6"
Provides-Extra: azure
Requires-Dist: azure-storage-blob (<=2.1,>=2.0.1) ; extra == 'azure'
Provides-Extra: gs
Requires-Dist: google-cloud-storage (>=1.13.2) ; extra == 'gs'
Provides-Extra: s3
Requires-Dist: boto3 (>=1.9) ; extra == 's3'
